dbt_graph_loader/README.md
dbt_graph_loader/__init__.py
dbt_graph_loader/cli.py
dbt_graph_loader/loaders/__init__.py
dbt_graph_loader/loaders/falkordb_loader.py
dbt_graph_loader/loaders/neo4j_loader.py
dbt_graph_loader-0.1.0a1.dist-info/LICENSE
dbt_graph_loader-0.1.0a1.dist-info/METADATA
dbt_graph_loader-0.1.0a1.dist-info/WHEEL
dbt_graph_loader-0.1.0a1.dist-info/entry_points.txt
dbt_graph_loader-0.1.0a1.dist-info/RECORD
