Metadata-Version: 2.3
Name: dbt-graph-loader
Version: 0.1.0a1
Summary: Load DBT metadata into graph databases (Neo4j and FalkorDB)
License: MIT
Keywords: dbt,graph,neo4j,falkordb,metadata,lineage
Author: Hipposys
Requires-Python: >=3.8,<4.0
Classifier: License :: OSI Approved :: MIT License
Classifier: Programming Language :: Python :: 3
Classifier: Programming Language :: Python :: 3.8
Classifier: Programming Language :: Python :: 3.9
Classifier: Programming Language :: Python :: 3.10
Classifier: Programming Language :: Python :: 3.11
Classifier: Programming Language :: Python :: 3.12
Classifier: Programming Language :: Python :: 3.13
Requires-Dist: click (>=8.0.0)
Requires-Dist: falkordb (>=1.0.0)
Requires-Dist: neo4j (>=5.0.0)
Project-URL: Repository, https://github.com/hipposys-ltd/dbt-kg
